{"frames": {

"7.png":
{
	"frame": {"x":0,"y":0,"w":100,"h":100},
	"rotated": false,
	"trimmed": false,
	"spriteSourceSize": {"x":0,"y":0,"w":100,"h":100},
	"sourceSize": {"w":100,"h":100}
},
"9.png":
{
	"frame": {"x":100,"y":0,"w":100,"h":100},
	"rotated": false,
	"trimmed": false,
	"spriteSourceSize": {"x":0,"y":0,"w":100,"h":100},
	"sourceSize": {"w":100,"h":100}
},
"10.png":
{
	"frame": {"x":0,"y":100,"w":100,"h":100},
	"rotated": false,
	"trimmed": false,
	"spriteSourceSize": {"x":0,"y":0,"w":100,"h":100},
	"sourceSize": {"w":100,"h":100}
},
"bitcoin.png":
{
	"frame": {"x":100,"y":100,"w":100,"h":100},
	"rotated": false,
	"trimmed": false,
	"spriteSourceSize": {"x":0,"y":0,"w":100,"h":100},
	"sourceSize": {"w":100,"h":100}
},
"bitcoin10.png":
{
	"frame": {"x":0,"y":200,"w":100,"h":100},
	"rotated": false,
	"trimmed": false,
	"spriteSourceSize": {"x":0,"y":0,"w":100,"h":100},
	"sourceSize": {"w":100,"h":100}
},
"dogecoin.png":
{
	"frame": {"x":100,"y":200,"w":100,"h":100},
	"rotated": false,
	"trimmed": false,
	"spriteSourceSize": {"x":0,"y":0,"w":100,"h":100},
	"sourceSize": {"w":100,"h":100}
},
"ethereumq.png":
{
	"frame": {"x":0,"y":300,"w":100,"h":100},
	"rotated": false,
	"trimmed": false,
	"spriteSourceSize": {"x":0,"y":0,"w":100,"h":100},
	"sourceSize": {"w":100,"h":100}
},
"j.png":
{
	"frame": {"x":100,"y":300,"w":100,"h":100},
	"rotated": false,
	"trimmed": false,
	"spriteSourceSize": {"x":0,"y":0,"w":100,"h":100},
	"sourceSize": {"w":100,"h":100}
},
"pepe-pepe-logo.png":
{
	"frame": {"x":0,"y":400,"w":100,"h":100},
	"rotated": false,
	"trimmed": false,
	"spriteSourceSize": {"x":0,"y":0,"w":100,"h":100},
	"sourceSize": {"w":100,"h":100}
},
"solana-sol-logo.png":
{
	"frame": {"x":100,"y":400,"w":100,"h":100},
	"rotated": false,
	"trimmed": false,
	"spriteSourceSize": {"x":0,"y":0,"w":100,"h":100},
	"sourceSize": {"w":100,"h":100}
},
"spin.png":
{
	"frame": {"x":0,"y":500,"w":189,"h":222},
	"rotated": false,
	"trimmed": false,
	"spriteSourceSize": {"x":0,"y":0,"w":189,"h":222},
	"sourceSize": {"w":189,"h":222}
},
"symbol2.png":
{
	"frame": {"x":0,"y":722,"w":100,"h":100},
	"rotated": false,
	"trimmed": false,
	"spriteSourceSize": {"x":0,"y":0,"w":100,"h":100},
	"sourceSize": {"w":100,"h":100}
},
"t.png":
{
	"frame": {"x":100,"y":722,"w":100,"h":100},
	"rotated": false,
	"trimmed": false,
	"spriteSourceSize": {"x":0,"y":0,"w":100,"h":100},
	"sourceSize": {"w":100,"h":100}
},
"tether-usdt-logo.png":
{
	"frame": {"x":0,"y":822,"w":100,"h":100},
	"rotated": false,
	"trimmed": false,
	"spriteSourceSize": {"x":0,"y":0,"w":100,"h":100},
	"sourceSize": {"w":100,"h":100}
},
"usd-coin-usdc-logo.png":
{
	"frame": {"x":100,"y":822,"w":100,"h":100},
	"rotated": false,
	"trimmed": false,
	"spriteSourceSize": {"x":0,"y":0,"w":100,"h":100},
	"sourceSize": {"w":100,"h":100}
},
"xrp-xrp-logo.png":
{
	"frame": {"x":0,"y":922,"w":100,"h":100},
	"rotated": false,
	"trimmed": false,
	"spriteSourceSize": {"x":0,"y":0,"w":100,"h":100},
	"sourceSize": {"w":100,"h":100}
}},
"meta": {
	"app": "https://www.codeandweb.com/texturepacker",
	"version": "1.0",
	"image": "spritesheethash.png",
	"format": "RGBA8888",
	"size": {"w":200,"h":1022},
	"scale": "1",
	"smartupdate": "$TexturePacker:SmartUpdate:1c552ba64c603dd63422835760afdd83:d52e925221588398af8b594a58292249:a9574fc2cc3150f193f1af0dc25132dd$"
}
}
